<?xml version="1.0" encoding="UTF-8"?>
<!DOCTYPE VNCLASS SYSTEM "vn_class-3.dtd">
<VNCLASS ID="nafaDa-1" xmlns:xsi="http://www.w3.org/2001/XMLSchema-instance" xsi:noNamespaceSchemaLocation="vn_schema-3.xsd">
    <MEMBERS>
        <MEMBER name="نَفَضَ" transliteration="nafaDa" transname="نفض" wn="">
            <Root name="نفض" transliteration="nfD"/>
            <Deverbal name="نَفْض" transliteration="nafoD" transname="نفض" wn=""/>
            <Active_participle name="نَافِض" transliteration="naAfiD" transname="نافض" wn=""/>
        </MEMBER>
        <MEMBER name="نَفّضَ" transliteration="naf~Da" transname="نفض" wn="">
            <Root name="نفض" transliteration="nfD"/>
            <Deverbal name="تَنْفِيض" transliteration="tanofiyD" transname="تنفيض" wn=""/>
            <Active_participle name="مُنَفِّض" transliteration="munaf~iD" transname="منفض" wn=""/>
        </MEMBER>
        <MEMBER name="كَسَحَ" transliteration="kasaHa" transname="كسح" wn="">
            <Root name="كسح" transliteration="ksH"/>
            <Deverbal name="كَسْح" transliteration="kasoH" transname="كسح" wn=""/>
            <Active_participle name="كَاسِح" transliteration="kaAsiH" transname="كاسح" wn=""/>
        </MEMBER>
        <MEMBER name="خَمَّ" transliteration="xam~a" transname="خم" wn="">
            <Root name="خمم" transliteration="xmm"/>
            <Deverbal name="خَمّ" transliteration="xam~" transname="خم" wn=""/>
            <Active_participle name="خَام" transliteration="xaAm" transname="خام" wn=""/>
        </MEMBER>
        <MEMBER name="قَمَّ" transliteration="qam~a" transname="قم" wn="">
            <Root name="قمم" transliteration="qmm"/>
            <Deverbal name="قَمّ" transliteration="qam~" transname="قم" wn=""/>
            <Active_participle name="قَام" transliteration="qaAm" transname="قام" wn=""/>
        </MEMBER>
        <MEMBER name="مَسَحَ" transliteration="masaHa" transname="مسح" wn="">
            <Root name="مسح" transliteration="msH"/>
            <Deverbal name="مَسْح" transliteration="masoH" transname="مسح" wn=""/>
            <Active_participle name="مَاسِح" transliteration="maAsiH" transname="ماسح" wn=""/>
        </MEMBER>
        <MEMBER name="مَحَى" transliteration="maHaY" transname="محى" wn="">
            <Root name="مها" transliteration="mhA"/>
            <Deverbal name="مَحْو" transliteration="maHow" transname="محو" wn=""/>
            <Active_participle name="مَاحِي" transliteration="maAHiy" transname="ماحي" wn=""/>
        </MEMBER>
        <MEMBER name="غَسَلَ" transliteration="gasala" transname="غسل" wn="">
            <Root name="غسل" transliteration="gsl"/>
            <Deverbal name="غَسْل" transliteration="gasol" transname="غسل" wn=""/>
            <Active_participle name="غَاسِل" transliteration="gaAsil" transname="غاسل" wn=""/>
        </MEMBER>
        <MEMBER name="رَحَضَ" transliteration="raHaDa" transname="رحض" wn="">
            <Root name="رحض" transliteration="rHD"/>
            <Deverbal name="رَحْض" transliteration="raHoD" transname="رحض" wn=""/>
            <Active_participle name="رَاحِض" transliteration="raAHiD" transname="راحض" wn=""/>
        </MEMBER>
        <MEMBER name="عَصَرَ" transliteration="EaSara" transname="عصر" wn="">
            <Root name="عصر" transliteration="ESr"/>
            <Deverbal name="عَصْر" transliteration="EaSor" transname="عصر" wn=""/>
            <Active_participle name="عَاصِر" transliteration="EaASir" transname="عاصر" wn=""/>
        </MEMBER>
        <MEMBER name="مَحَصَ" transliteration="maHaSa" transname="محص" wn="">
            <Root name="محص" transliteration="mHS"/>
            <Deverbal name="مَحْص" transliteration="maHoS" transname="محص" wn=""/>
            <Active_participle name="مَاحِص" transliteration="maAHiS" transname="ماحص" wn=""/>
        </MEMBER>
        <MEMBER name="نَفَضَ" transliteration="nafaDa" transname="نفض" wn="">
            <Root name="نفض" transliteration="nfD"/>
            <Deverbal name="نَفْض" transliteration="nafoD" transname="نفض" wn=""/>
            <Active_participle name="نَافِض" transliteration="naAfiD" transname="نافض" wn=""/>
        </MEMBER>
        <MEMBER name="مَحَّصَ" transliteration="maH~aSa" transname="محص" wn="">
            <Root name="محص" transliteration="mHS"/>
            <Deverbal name="تَمْحِيص" transliteration="tamoHiyS" transname="تمحيص" wn=""/>
            <Active_participle name="مُمَحِّص" transliteration="mumaH~iS" transname="ممحص" wn=""/>
        </MEMBER>
    </MEMBERS>
    <THEMROLES>
        <THEMROLE type="Agent">
            <SELRESTRS>
                <SELRESTR Value="+" type="int_control"/>
            </SELRESTRS>
        </THEMROLE>
        <THEMROLE type="Theme">
            <SELRESTRS>
                <SELRESTR Value="+" type="concrete"/>
                <SELRESTR Value="-" type="animate"/>
            </SELRESTRS>
        </THEMROLE>
        <THEMROLE type="Source">
            <SELRESTRS>
                <SELRESTR Value="+" type="location"/>
            </SELRESTRS>
        </THEMROLE>
    </THEMROLES>
    <FRAMES>
        <FRAME>
            <DESCRIPTION descriptionNumber="0.2" primary="V NP NP PP.source" secondary="NP-PPSource-PP" xtag=""/>
            <EXAMPLES>
                <EXAMPLE sentence="مَسَحَ النَّادِلُ المَرَقَ مِنْ (عَلَى) المَائِدَة." transliteration="masaHa Aln~aAdilu Almaraqa mino (EalaY) AlmaA}idap."/>
            </EXAMPLES>
            <SYNTAX>
                <VERB/>
                <NP value="Agent">
                    <SYNRESTRS/>
                </NP>
                <NP value="Theme">
                    <SYNRESTRS/>
                </NP>
                <PREP>
                    <SELRESTRS>
                        <SELRESTR Value="+" type="src"/>
                    </SELRESTRS>
                </PREP>
                <NP value="Source">
                    <SYNRESTRS/>
                </NP>
            </SYNTAX>
            <SEMANTICS>
                <PRED value="cause">
                    <ARGS>
                        <ARG type="ThemRole" value="Agent"/>
                        <ARG type="Event" value="E"/>
                    </ARGS>
                </PRED>
                <PRED value="location">
                    <ARGS>
                        <ARG type="Event" value="start(E)"/>
                        <ARG type="ThemRole" value="Theme"/>
                        <ARG type="ThemRole" value="Source"/>
                    </ARGS>
                </PRED>
                <PRED bool="!" value="location">
                    <ARGS>
                        <ARG type="Event" value="end(E)"/>
                        <ARG type="ThemRole" value="Theme"/>
                        <ARG type="ThemRole" value="Source"/>
                    </ARGS>
                </PRED>
            </SEMANTICS>
        </FRAME>
        <FRAME>
            <DESCRIPTION descriptionNumber="0.2" primary="V NP NP.source" secondary="TransitiveSource Object" xtag="0.2"/>
            <EXAMPLES>
                <EXAMPLE sentence="مَسَحَ النَّادِلُ المَائِدَةَ." transliteration="masaHa Aln~aAdilu AlmaA}idapa."/>
            </EXAMPLES>
            <SYNTAX>
                <VERB/>
                <NP value="Agent">
                    <SYNRESTRS/>
                </NP>
                <NP value="Source">
                    <SYNRESTRS/>
                </NP>
            </SYNTAX>
            <SEMANTICS>
                <PRED value="cause">
                    <ARGS>
                        <ARG type="ThemRole" value="Agent"/>
                        <ARG type="Event" value="E"/>
                    </ARGS>
                </PRED>
                <PRED value="location">
                    <ARGS>
                        <ARG type="Event" value="start(E)"/>
                        <ARG type="ThemRole" value="?Theme"/>
                        <ARG type="ThemRole" value="Source"/>
                    </ARGS>
                </PRED>
                <PRED bool="!" value="location">
                    <ARGS>
                        <ARG type="Event" value="end(E)"/>
                        <ARG type="ThemRole" value="?Theme"/>
                        <ARG type="ThemRole" value="Source"/>
                    </ARGS>
                </PRED>
            </SEMANTICS>
        </FRAME>
        <FRAME>
            <DESCRIPTION descriptionNumber="" primary="V NP NP.theme" secondary="TransitiveTheme Object" xtag=""/>
            <EXAMPLES>
                <EXAMPLE sentence="مَسَحَ النَّادِلُ المَرَقَ." transliteration="masaHa Aln~aAdilu Almaraqa."/>
            </EXAMPLES>
            <SYNTAX>
                <VERB/>
                <NP value="Agent">
                    <SYNRESTRS/>
                </NP>
                <NP value="Theme">
                    <SYNRESTRS/>
                </NP>
            </SYNTAX>
            <SEMANTICS>
                <PRED value="cause">
                    <ARGS>
                        <ARG type="ThemRole" value="Agent"/>
                        <ARG type="Event" value="E"/>
                    </ARGS>
                </PRED>
                <PRED value="location">
                    <ARGS>
                        <ARG type="Event" value="start(E)"/>
                        <ARG type="ThemRole" value="Theme"/>
                        <ARG type="ThemRole" value="?Source"/>
                    </ARGS>
                </PRED>
                <PRED bool="!" value="location">
                    <ARGS>
                        <ARG type="Event" value="end(E)"/>
                        <ARG type="ThemRole" value="Theme"/>
                        <ARG type="ThemRole" value="?Source"/>
                    </ARGS>
                </PRED>
            </SEMANTICS>
        </FRAME>
    </FRAMES>
    <SUBCLASSES/>
    <SIBLINGCLASSES/>
</VNCLASS>
